{
 "id": 1,
 "body": {
  "part": [
   {
    "id": "Core",
    "type": "CoreComponent",
    "root": true,
    "orientation": 0
   },
   {
    "id": "Hip1",
    "type": "ActiveHinge",
    "root": false,
    "orientation": 1
   },
   {
    "id": "UpperLeg1",
    "type": "FixedBrick",
    "root": false,
    "orientation": 1
   },
   {
    "id": "Hip2",
    "type": "ActiveHinge",
    "root": false,
    "orientation": 3
   },
   {
    "id": "UpperLeg2",
    "type": "FixedBrick",
    "root": false,
    "orientation": 1
   },
   {
    "id": "Knee2",
    "type": "ActiveHinge",
    "root": false,
    "orientation": 0
   },
   {
    "id": "LowerLeg2",
    "type": "FixedBrick",
    "root": false,
    "orientation": 0
   },
   {
    "id": "Hip3",
    "type": "ActiveHinge",
    "root": false,
    "orientation": 3
   },
   {
    "id": "UpperLeg3",
    "type": "FixedBrick",
    "root": false,
    "orientation": 1
   },
   {
    "id": "Knee3",
    "type": "ActiveHinge",
    "root": false,
    "orientation": 0
   },
   {
    "id": "LowerLeg3",
    "type": "FixedBrick",
    "root": false,
    "orientation": 0
   }
  ],
  "connection": [
   {
    "src": "Core",
    "dest": "Hip1",
    "srcSlot": 0,
    "destSlot": 0
   },
   {
    "src": "Hip1",
    "dest": "UpperLeg1",
    "srcSlot": 1,
    "destSlot": 0
   },
   {
    "src": "Core",
    "dest": "Hip2",
    "srcSlot": 1,
    "destSlot": 0
   },
   {
    "src": "Hip2",
    "dest": "UpperLeg2",
    "srcSlot": 1,
    "destSlot": 0
   },
   {
    "src": "UpperLeg2",
    "dest": "Knee2",
    "srcSlot": 1,
    "destSlot": 0
   },
   {
    "src": "Knee2",
    "dest": "LowerLeg2",
    "srcSlot": 1,
    "destSlot": 0
   },
   {
    "src": "Core",
    "dest": "Hip3",
    "srcSlot": 2,
    "destSlot": 0
   },
   {
    "src": "Hip3",
    "dest": "UpperLeg3",
    "srcSlot": 1,
    "destSlot": 0
   },
   {
    "src": "UpperLeg3",
    "dest": "Knee3",
    "srcSlot": 1,
    "destSlot": 0
   },
   {
    "src": "Knee3",
    "dest": "LowerLeg3",
    "srcSlot": 1,
    "destSlot": 0
   }
  ]
 },
 "brain": {
  "neuron": [
   {
    "id": "Core-0",
    "layer": "input",
    "type": "simple",
    "bodyPartId": "Core",
    "ioId": 0,
    "gain": 1.0
   },
   {
    "id": "Core-1",
    "layer": "input",
    "type": "simple",
    "bodyPartId": "Core",
    "ioId": 1,
    "gain": 1.0
   },
   {
    "id": "Core-2",
    "layer": "input",
    "type": "simple",
    "bodyPartId": "Core",
    "ioId": 2,
    "gain": 1.0
   },
   {
    "id": "Core-3",
    "layer": "input",
    "type": "simple",
    "bodyPartId": "Core",
    "ioId": 3,
    "gain": 1.0
   },
   {
    "id": "Core-4",
    "layer": "input",
    "type": "simple",
    "bodyPartId": "Core",
    "ioId": 4,
    "gain": 1.0
   },
   {
    "id": "Core-5",
    "layer": "input",
    "type": "simple",
    "bodyPartId": "Core",
    "ioId": 5,
    "gain": 1.0
   },
   {
    "id": "Hip1-0",
    "layer": "output",
    "type": "oscillator",
    "bodyPartId": "Hip1",
    "ioId": 0,
    "phaseOffset": -0.4679943323135376,
    "period": 0.033580534160137177,
    "gain": 0.30128899216651917
   },
   {
    "id": "Hip2-0",
    "layer": "output",
    "type": "oscillator",
    "bodyPartId": "Hip2",
    "ioId": 0,
    "phaseOffset": 0.44776737689971924,
    "period": 0.17346397042274475,
    "gain": 0.69689458608627319
   },
   {
    "id": "Hip3-0",
    "layer": "output",
    "type": "sigmoid",
    "bias": -0.67591869831085205,
    "bodyPartId": "Hip3",
    "ioId": 0,
    "gain": 1.0
   },
   {
    "id": "Knee2-0",
    "layer": "output",
    "type": "oscillator",
    "bodyPartId": "Knee2",
    "ioId": 0,
    "phaseOffset": 0.86956459283828735,
    "period": 0.55337673425674438,
    "gain": 0.081629559397697449
   },
   {
    "id": "Knee3-0",
    "layer": "output",
    "type": "sigmoid",
    "bias": -0.57003539800643921,
    "bodyPartId": "Knee3",
    "ioId": 0,
    "gain": 1.0
   }
  ],
  "connection": [
   {
    "src": "Core-0",
    "dest": "Hip3-0",
    "weight": 0.15040047466754913
   },
   {
    "src": "Core-0",
    "dest": "Knee3-0",
    "weight": -0.05131637305021286
   },
   {
    "src": "Core-1",
    "dest": "Hip3-0",
    "weight": -0.44613590836524963
   },
   {
    "src": "Core-1",
    "dest": "Knee3-0",
    "weight": -1.6037430763244629
   },
   {
    "src": "Core-2",
    "dest": "Hip3-0",
    "weight": 1.1929712295532227
   },
   {
    "src": "Core-2",
    "dest": "Knee3-0",
    "weight": -1.9316530227661133
   },
   {
    "src": "Core-3",
    "dest": "Hip3-0",
    "weight": 2.940333366394043
   },
   {
    "src": "Core-3",
    "dest": "Knee3-0",
    "weight": 2.7648322582244873
   },
   {
    "src": "Core-4",
    "dest": "Hip3-0",
    "weight": 0.17555361986160278
   },
   {
    "src": "Core-4",
    "dest": "Knee3-0",
    "weight": -0.84081906080245972
   },
   {
    "src": "Core-5",
    "dest": "Hip3-0",
    "weight": 2.273442268371582
   },
   {
    "src": "Core-5",
    "dest": "Knee3-0",
    "weight": 2.3718883991241455
   },
   {
    "src": "Hip1-0",
    "dest": "Hip3-0",
    "weight": 0.93726766109466553
   },
   {
    "src": "Hip1-0",
    "dest": "Knee3-0",
    "weight": 2.4980530738830566
   },
   {
    "src": "Hip2-0",
    "dest": "Hip3-0",
    "weight": -0.81722801923751831
   },
   {
    "src": "Hip2-0",
    "dest": "Knee3-0",
    "weight": -0.4330919086933136
   },
   {
    "src": "Hip3-0",
    "dest": "Hip3-0",
    "weight": -0.91350752115249634
   },
   {
    "src": "Hip3-0",
    "dest": "Knee3-0",
    "weight": 0.51950854063034058
   },
   {
    "src": "Knee2-0",
    "dest": "Hip3-0",
    "weight": 3.0
   },
   {
    "src": "Knee2-0",
    "dest": "Knee3-0",
    "weight": -3.0
   },
   {
    "src": "Knee3-0",
    "dest": "Hip3-0",
    "weight": -2.0291013717651367
   },
   {
    "src": "Knee3-0",
    "dest": "Knee3-0",
    "weight": -2.637706995010376
   }
  ]
 }
}